README.md
setup.cfg
setup.py
lp_unittest/__init__.py
lp_unittest/apps.py
lp_unittest/helpers.py
lp_unittest.egg-info/PKG-INFO
lp_unittest.egg-info/SOURCES.txt
lp_unittest.egg-info/dependency_links.txt
lp_unittest.egg-info/requires.txt
lp_unittest.egg-info/top_level.txt
lp_unittest/migrations/__init__.py