Metadata-Version: 1.1
Name: lp-unittest
Version: 1.0.1
Summary: REST Unit Test Framework
Home-page: https://github.com/Launchpeer/django-rest-unit-tests
Author: Jim Simon
Author-email: hello@launchpeer.com
License: UNKNOWN
Download-URL: https://github.com/Launchpeer/django-rest-unit-tests/archive/master.tar.gz
Platform: UNKNOWN
